odoo/addons/stock_dock/README.rst
odoo/addons/stock_dock/__init__.py
odoo/addons/stock_dock/__manifest__.py
odoo/addons/stock_dock/demo/stock_dock.xml
odoo/addons/stock_dock/i18n/it.po
odoo/addons/stock_dock/i18n/stock_dock.pot
odoo/addons/stock_dock/models/__init__.py
odoo/addons/stock_dock/models/stock_dock.py
odoo/addons/stock_dock/readme/CONTRIBUTORS.rst
odoo/addons/stock_dock/readme/CREDITS.rst
odoo/addons/stock_dock/readme/DESCRIPTION.rst
odoo/addons/stock_dock/security/ir.model.access.csv
odoo/addons/stock_dock/static/description/icon.png
odoo/addons/stock_dock/static/description/index.html
odoo/addons/stock_dock/views/stock_dock.xml
odoo14_addon_stock_dock-14.0.1.2.0.dist-info/METADATA
odoo14_addon_stock_dock-14.0.1.2.0.dist-info/WHEEL
odoo14_addon_stock_dock-14.0.1.2.0.dist-info/top_level.txt
odoo14_addon_stock_dock-14.0.1.2.0.dist-info/RECORD
